greenws.py
greenws-0.1.0a7.dist-info/LICENSE
greenws-0.1.0a7.dist-info/WHEEL
greenws-0.1.0a7.dist-info/METADATA
greenws-0.1.0a7.dist-info/RECORD
