Metadata-Version: 2.1
Name: greenws
Version: 0.1.0a7
Summary: WebSockets for gevent.
Author-email: Auri <me@aurieh.me>
Requires-Python: >=3.7
Classifier: Development Status :: 2 - Pre-Alpha
Classifier: Environment :: Web Environment
Classifier: License :: OSI Approved :: BSD License
Classifier: Operating System :: OS Independent
Classifier: Programming Language :: Python :: 3 :: Only
Classifier: Programming Language :: Python :: 3.7
Classifier: Topic :: Internet :: WWW/HTTP
Requires-Dist: gevent
Requires-Dist: wsproto ~= 1.0.0
Project-URL: Code, https://github.com/quasar-media/python-greenws
Project-URL: Documentation, https://greenws.rtfd.io
